pypower/__init__.py
pypower/_compat.py
pypower/add_userfcn.py
pypower/api.py
pypower/bustypes.py
pypower/case118.py
pypower/case14.py
pypower/case24_ieee_rts.py
pypower/case30.py
pypower/case300.py
pypower/case30Q.py
pypower/case30pwl.py
pypower/case39.py
pypower/case4gs.py
pypower/case57.py
pypower/case6ww.py
pypower/case9.py
pypower/case9Q.py
pypower/case9target.py
pypower/caseformat.py
pypower/cpf_callbacks.py
pypower/cpf_corrector.py
pypower/cpf_p.py
pypower/cpf_p_jac.py
pypower/cpf_predictor.py
pypower/cplex_options.py
pypower/d2AIbr_dV2.py
pypower/d2ASbr_dV2.py
pypower/d2Ibr_dV2.py
pypower/d2Sbr_dV2.py
pypower/d2Sbus_dV2.py
pypower/dAbr_dV.py
pypower/dIbr_dV.py
pypower/dSbr_dV.py
pypower/dSbus_dV.py
pypower/dcopf.py
pypower/dcopf_solver.py
pypower/dcpf.py
pypower/e2i_data.py
pypower/e2i_field.py
pypower/ext2int.py
pypower/fairmax.py
pypower/fdpf.py
pypower/gausspf.py
pypower/get_reorder.py
pypower/gurobi_options.py
pypower/hasPQcap.py
pypower/i2e_data.py
pypower/i2e_field.py
pypower/idx_area.py
pypower/idx_brch.py
pypower/idx_bus.py
pypower/idx_cost.py
pypower/idx_dcline.py
pypower/idx_gen.py
pypower/int2ext.py
pypower/ipopt_options.py
pypower/ipoptopf_solver.py
pypower/isload.py
pypower/loadcase.py
pypower/main.py
pypower/makeAang.py
pypower/makeApq.py
pypower/makeAvl.py
pypower/makeAy.py
pypower/makeB.py
pypower/makeBdc.py
pypower/makeLODF.py
pypower/makePTDF.py
pypower/makeSbus.py
pypower/makeYbus.py
pypower/modcost.py
pypower/mosek_options.py
pypower/newtonpf.py
pypower/opf.py
pypower/opf_args.py
pypower/opf_consfcn.py
pypower/opf_costfcn.py
pypower/opf_execute.py
pypower/opf_hessfcn.py
pypower/opf_model.py
pypower/opf_setup.py
pypower/pfsoln.py
pypower/pips.py
pypower/pipsopf_solver.py
pypower/pipsver.py
pypower/poly2pwl.py
pypower/polycost.py
pypower/pplinsolve.py
pypower/ppoption.py
pypower/ppver.py
pypower/pqcost.py
pypower/printpf.py
pypower/qps_cplex.py
pypower/qps_gurobi.py
pypower/qps_ipopt.py
pypower/qps_mosek.py
pypower/qps_pips.py
pypower-5.1.18.dist-info/licenses/AUTHORS
pypower-5.1.18.dist-info/licenses/LICENSE
pypower-5.1.18.dist-info/METADATA
pypower-5.1.18.dist-info/WHEEL
pypower-5.1.18.dist-info/entry_points.txt
pypower-5.1.18.dist-info/top_level.txt
pypower-5.1.18.dist-info/RECORD
